midiscript/__init__.py
midiscript/cli.py
midiscript/lexer.py
midiscript/midi_generator.py
midiscript/parser.py
midiscript-0.2.4.dist-info/LICENSE
midiscript-0.2.4.dist-info/METADATA
midiscript-0.2.4.dist-info/WHEEL
midiscript-0.2.4.dist-info/entry_points.txt
midiscript-0.2.4.dist-info/top_level.txt
midiscript-0.2.4.dist-info/RECORD
